oxylabs_ai_studio/__init__.py
oxylabs_ai_studio/client.py
oxylabs_ai_studio/logger.py
oxylabs_ai_studio/models.py
oxylabs_ai_studio/settings.py
oxylabs_ai_studio/utils.py
oxylabs_ai_studio/apps/ai_crawler.py
oxylabs_ai_studio/apps/ai_map.py
oxylabs_ai_studio/apps/ai_scraper.py
oxylabs_ai_studio/apps/ai_search.py
oxylabs_ai_studio/apps/browser_agent.py
oxylabs_ai_studio-0.2.20.dist-info/METADATA
oxylabs_ai_studio-0.2.20.dist-info/WHEEL
oxylabs_ai_studio-0.2.20.dist-info/licenses/LICENSE
oxylabs_ai_studio-0.2.20.dist-info/RECORD
