Metadata-Version: 2.4
Name: oxylabs-ai-studio
Version: 0.2.20
Summary: Oxylabs studio python sdk
License-File: LICENSE
Keywords: ai,oxylabs,studio
Requires-Python: >=3.10
Requires-Dist: httpx>=0.28.1
Requires-Dist: pydantic-settings>=2.9.1
Requires-Dist: pydantic>=2.0.0
Requires-Dist: python-dotenv>=1.1.0
Requires-Dist: tenacity>=9.1.2
